localpkg/__init__.py
localpkg/main.py
localpkg/version.py
localpkg-0.2.dist-info/licenses/LICENSE
localpkg-0.2.dist-info/METADATA
localpkg-0.2.dist-info/WHEEL
localpkg-0.2.dist-info/entry_points.txt
localpkg-0.2.dist-info/top_level.txt
localpkg-0.2.dist-info/RECORD
