Metadata-Version: 2.4
Name: localpkg
Version: 0.2
Summary: local package creator
Home-page: https://github.com/wtnb75/localpkg
Author: Watanabe Takashi
Author-email: wtnb75@gmail.com
License: MIT
Classifier: Development Status :: 3 - Alpha
Classifier: Intended Audience :: Developers
Classifier: Programming Language :: Python :: 3
License-File: LICENSE
Requires-Dist: click
Provides-Extra: dev
Requires-Dist: pytest; extra == "dev"
Requires-Dist: pytest-cov; extra == "dev"
Dynamic: license-file
Dynamic: provides-extra
Dynamic: requires-dist
